bcscraper/__init__.py
bcscraper/classes.py
bcscraper/main.py
bcscraper/utils.py
bcscraper-0.0.3.dist-info/licenses/LICENSE
bcscraper-0.0.3.dist-info/METADATA
bcscraper-0.0.3.dist-info/WHEEL
bcscraper-0.0.3.dist-info/top_level.txt
bcscraper-0.0.3.dist-info/RECORD
