Metadata-Version: 2.4
Name: bcscraper
Version: 0.0.3
Summary: Un scraper para buscacursos.uc.cl.
Author: Víctor Moreno
Author-email: vicmoor07@gmail.com
Maintainer: Víctor Moreno
Maintainer-email: vicmoor07@gmail.com
License: MIT
Keywords: scraper,buscacursos,uc
License-File: LICENSE
Requires-Dist: beautifulsoup4>=4.14.3
Requires-Dist: cloudscraper>=1.2.71
Dynamic: author
Dynamic: author-email
Dynamic: description
Dynamic: keywords
Dynamic: license
Dynamic: license-file
Dynamic: maintainer
Dynamic: maintainer-email
Dynamic: requires-dist
Dynamic: summary
